odoo/addons/dms_attachment_link/README.rst
odoo/addons/dms_attachment_link/__init__.py
odoo/addons/dms_attachment_link/__manifest__.py
odoo/addons/dms_attachment_link/i18n/dms_attachment_link.pot
odoo/addons/dms_attachment_link/i18n/es.po
odoo/addons/dms_attachment_link/models/__init__.py
odoo/addons/dms_attachment_link/models/dms_file.py
odoo/addons/dms_attachment_link/models/ir_attachment.py
odoo/addons/dms_attachment_link/readme/CONTRIBUTORS.rst
odoo/addons/dms_attachment_link/readme/DESCRIPTION.rst
odoo/addons/dms_attachment_link/readme/USAGE.rst
odoo/addons/dms_attachment_link/static/description/icon.png
odoo/addons/dms_attachment_link/static/description/icon.svg
odoo/addons/dms_attachment_link/static/description/index.html
odoo/addons/dms_attachment_link/static/src/js/dms_attachment_link.js
odoo/addons/dms_attachment_link/static/src/xml/chatter.xml
odoo/addons/dms_attachment_link/tests/__init__.py
odoo/addons/dms_attachment_link/tests/test_dms_attachment_link.py
odoo/addons/dms_attachment_link/views/assets.xml
odoo/addons/dms_attachment_link/views/dms_file_views.xml
odoo13_addon_dms_attachment_link-13.0.1.1.0.dist-info/METADATA
odoo13_addon_dms_attachment_link-13.0.1.1.0.dist-info/WHEEL
odoo13_addon_dms_attachment_link-13.0.1.1.0.dist-info/top_level.txt
odoo13_addon_dms_attachment_link-13.0.1.1.0.dist-info/RECORD
